{
  "pups": [
    {
      "id": 1,
      "name": "Mr. Bonkers",
      "image": "https://curriculum-content.s3.amazonaws.com/js/woof-woof/dog_1.jpg",
      "isGoodDog": false
    },
    {
      "id": 2,
      "name": "Nugget",
      "image": "https://curriculum-content.s3.amazonaws.com/js/woof-woof/dog_2.jpg",
      "isGoodDog": false
    },
    {
      "id": 3,
      "name": "Skittles",
      "image": "https://curriculum-content.s3.amazonaws.com/js/woof-woof/dog_3.jpg",
      "isGoodDog": true
    },
    {
      "id": 4,
      "name": "Buttercup",
      "image": "https://curriculum-content.s3.amazonaws.com/js/woof-woof/dog_4.jpg",
      "isGoodDog": true
    },
    {
      "id": 5,
      "name": "Lucipher",
      "image": "https://curriculum-content.s3.amazonaws.com/js/woof-woof/dog_5.jpg",
      "isGoodDog": true
    },
    {
      "id": 6,
      "name": "Snooper Pooper",
      "image": "https://curriculum-content.s3.amazonaws.com/js/woof-woof/dog_6.jpg",
      "isGoodDog": true
    },
    {
      "id": 7,
      "name": "Puddles",
      "image": "https://curriculum-content.s3.amazonaws.com/js/woof-woof/dog_7.jpg",
      "isGoodDog": false
    },
    {
      "id": 8,
      "name": "Mittens",
      "image": "https://curriculum-content.s3.amazonaws.com/js/woof-woof/dog_1.jpg",
      "isGoodDog": false
    },
    {
      "id": 9,
      "name": "Middens",
      "image": "https://curriculum-content.s3.amazonaws.com/js/woof-woof/dog_2.jpg",
      "isGoodDog": false
    },
    {
      "id": 10,
      "name": "Fido",
      "image": "https://curriculum-content.s3.amazonaws.com/js/woof-woof/dog_5.jpg",
      "isGoodDog": false
    }
  ]
}